{
    "Schedule": [
        {
            "Понедельник": [
                {
                    "Time": "08:00",
                    "Matter": "Производственное обучение УО \"Минский индустриально- педагогический колледж филлиал, 6 часов",
                    "Teacher": "",
                    "Frame": "Республиканский институт профессионального образования",
                    "Classroom": ""
                },
                {
                    "Time": "15:40",
                    "Matter": "ОИЗ, Математика",
                    "Teacher": "доц. Гундина М. А.",
                    "Frame": "8",
                    "Classroom": "422"
                }
            ],
            "Вторник": [
                {
                    "Time": "08:00",
                    "Matter": "(Лекц.) Информатика",
                    "Teacher": "пр. Михасик Е. И.",
                    "Frame": "1",
                    "Classroom": "450"
                },
                {
                    "Time": "09:55",
                    "Matter": "(Лекц.) Физика",
                    "Teacher": "проф. Князев М. А.",
                    "Frame": "17",
                    "Classroom": "3П"
                },
                {
                    "Time": "12:10",
                    "Matter": "Физическая культура",
                    "Teacher": "ст.пр. Анципорович Н. П. Миклашевич Е. Ю.",
                    "Frame": "",
                    "Classroom": ""
                }
            ],
            "Среда": [
                {
                    "Time": "08:00",
                    "Matter": "(Лаб.) Физика, 1/2 группы ",
                    "Teacher": "доц. Красовский В. В.",
                    "Frame": "17",
                    "Classroom": "412"
                },
                {
                    "Time": "08:00",
                    "Matter": "(Лаб.) Физика, 1/2 группы ",
                    "Teacher": "доц. Красовский В. В.",
                    "Frame": "17",
                    "Classroom": "401"
                },
                {
                    "Time": "09:55",
                    "Matter": "(Лаб.) Физика, 1/2 группы ",
                    "Teacher": "доц. Красовский В. В.",
                    "Frame": "17",
                    "Classroom": "401"
                },
                {
                    "Time": "09:55",
                    "Matter": "(Лаб.) Физика, 1/2 группы ",
                    "Teacher": "доц. Красовский В. В.",
                    "Frame": "17",
                    "Classroom": "412"
                },
                {
                    "Time": "11:40",
                    "Matter": "(Практ.) Математика",
                    "Teacher": "",
                    "Frame": "17",
                    "Classroom": "506"
                },
                {
                    "Time": "13:55",
                    "Matter": "(Лекц.) Электротехнические материалы Артеменко, 1/2 группы ",
                    "Teacher": "",
                    "Frame": "2",
                    "Classroom": "1"
                }
            ],
            "Четверг": [
                {
                    "Time": "08:00",
                    "Matter": "(Лекц.) Математика",
                    "Teacher": "доц. Гундина М. А.",
                    "Frame": "17",
                    "Classroom": "2П"
                },
                {
                    "Time": "09:55",
                    "Matter": "(Практ.) Химия, 1/2 группы ",
                    "Teacher": "",
                    "Frame": "11",
                    "Classroom": "506"
                },
                {
                    "Time": "09:55",
                    "Matter": "(Практ.) Химия, 1/2 группы ",
                    "Teacher": "",
                    "Frame": "11",
                    "Classroom": "510"
                },
                {
                    "Time": "11:40",
                    "Matter": "(Лаб.) английский язык английский язык, 1/2 группы ",
                    "Teacher": "ст.пр. Здоронок Ю. А.",
                    "Frame": "1",
                    "Classroom": "440"
                },
                {
                    "Time": "11:40",
                    "Matter": "(Лаб.) английский язык английский язык, 1/2 группы ",
                    "Teacher": "ст.пр. Якушева Н. В.",
                    "Frame": "18",
                    "Classroom": "410"
                },
                {
                    "Time": "13:55",
                    "Matter": "(Практ.) английский язык, 1/2 группы ",
                    "Teacher": "ст.пр. Здоронок Ю. А.",
                    "Frame": "1",
                    "Classroom": "440"
                }
            ],
            "Пятница": [
                {
                    "Time": "08:00",
                    "Matter": "(Практ.) Инженерная графика",
                    "Teacher": "ст.пр. Тявловская Т. М.",
                    "Frame": "8",
                    "Classroom": "522"
                },
                {
                    "Time": "10:25",
                    "Matter": "(Лекц.) Введение в инженерно-педагогическое образование",
                    "Teacher": "ст.пр. Игнаткович И. В.",
                    "Frame": "20",
                    "Classroom": "601"
                },
                {
                    "Time": "12:10",
                    "Matter": "Физическая культура",
                    "Teacher": "ст.пр. Анципорович Н. П. Миклашевич Е. Ю.",
                    "Frame": "",
                    "Classroom": ""
                },
                {
                    "Time": "14:15",
                    "Matter": "(Лаб.) Информатика, 1/2 группы ",
                    "Teacher": "доц. Евтухова Т. Е.",
                    "Frame": "20",
                    "Classroom": "301"
                },
                {
                    "Time": "14:15",
                    "Matter": "(Лаб.) Информатика, 1/2 группы ",
                    "Teacher": "доц. Евтухова Т. Е.",
                    "Frame": "20",
                    "Classroom": "303"
                }
            ],
            "Суббота": [
                {
                    "Time": "08:00",
                    "Matter": "ОИЗ Инженерная графика",
                    "Teacher": "",
                    "Frame": "8",
                    "Classroom": "519"
                },
                {
                    "Time": "09:55",
                    "Matter": "(Лекц.) Химия",
                    "Teacher": "доц. Бурак Г. А.",
                    "Frame": "11",
                    "Classroom": "507"
                },
                {
                    "Time": "11:40",
                    "Matter": "(Лекц.) Инженерная графика",
                    "Teacher": "ст.пр. Хмельницкая Л. В.",
                    "Frame": "11",
                    "Classroom": "507"
                },
                {
                    "Time": "13:55",
                    "Matter": "ОИЗ Математика Шамонин",
                    "Teacher": "",
                    "Frame": "17",
                    "Classroom": "203"
                }
            ]
        },
        {
            "Понедельник": [
                {
                    "Time": "08:00",
                    "Matter": "Производственное обучение УО \"Минский индустриально- педагогический колледж филлиал, 6 часов",
                    "Teacher": "",
                    "Frame": "Республиканский институт профессионального образования",
                    "Classroom": ""
                }
            ],
            "Вторник": [
                {
                    "Time": "08:00",
                    "Matter": "(Практ.) Химия, 1/2 группы ",
                    "Teacher": "",
                    "Frame": "11",
                    "Classroom": "510"
                },
                {
                    "Time": "08:00",
                    "Matter": "(Практ.) Химия, 1/2 группы ",
                    "Teacher": "",
                    "Frame": "11",
                    "Classroom": "506"
                },
                {
                    "Time": "09:55",
                    "Matter": "(Лекц.) Физика",
                    "Teacher": "проф. Князев М. А.",
                    "Frame": "17",
                    "Classroom": "3П"
                },
                {
                    "Time": "12:10",
                    "Matter": "Физическая культура",
                    "Teacher": "ст.пр. Анципорович Н. П. Миклашевич Е. Ю.",
                    "Frame": "",
                    "Classroom": ""
                }
            ],
            "Среда": [
                {
                    "Time": "08:00",
                    "Matter": "(Лекц.) Электротехнические материалы",
                    "Teacher": "",
                    "Frame": "2",
                    "Classroom": "214"
                },
                {
                    "Time": "09:55",
                    "Matter": "(Лекц.) Электротехнические материалы",
                    "Teacher": "",
                    "Frame": "2",
                    "Classroom": "214"
                },
                {
                    "Time": "11:40",
                    "Matter": "(Практ.) Математика",
                    "Teacher": "",
                    "Frame": "17",
                    "Classroom": "506"
                },
                {
                    "Time": "13:55",
                    "Matter": "(Лекц.) Электротехнические материалы Артеменко, 1/2 группы ",
                    "Teacher": "",
                    "Frame": "2",
                    "Classroom": "1"
                }
            ],
            "Четверг": [
                {
                    "Time": "08:00",
                    "Matter": "(Лекц.) Математика",
                    "Teacher": "доц. Гундина М. А.",
                    "Frame": "17",
                    "Classroom": "2П"
                },
                {
                    "Time": "09:55",
                    "Matter": "(Практ.) Инженерная графика",
                    "Teacher": "ст.пр. Тявловская Т. М.",
                    "Frame": "8",
                    "Classroom": "510"
                },
                {
                    "Time": "11:40",
                    "Matter": "(Лаб.) английский язык английский язык, 1/2 группы ",
                    "Teacher": "ст.пр. Здоронок Ю. А.",
                    "Frame": "1",
                    "Classroom": "440"
                },
                {
                    "Time": "11:40",
                    "Matter": "(Лаб.) английский язык английский язык, 1/2 группы ",
                    "Teacher": "ст.пр. Якушева Н. В.",
                    "Frame": "18",
                    "Classroom": "410"
                },
                {
                    "Time": "13:55",
                    "Matter": "(Практ.) Физика",
                    "Teacher": "проф. Князев М. А.",
                    "Frame": "17",
                    "Classroom": "506"
                },
                {
                    "Time": "15:40",
                    "Matter": "ОИЗ Физика",
                    "Teacher": "проф. Князев М. А.",
                    "Frame": "1",
                    "Classroom": "458"
                }
            ],
            "Пятница": [
                {
                    "Time": "10:25",
                    "Matter": "(Практ.) английский язык, 1/2 группы ",
                    "Teacher": "ст.пр. Якушева Н. В.",
                    "Frame": "20",
                    "Classroom": "606"
                },
                {
                    "Time": "12:10",
                    "Matter": "Физическая культура",
                    "Teacher": "ст.пр. Анципорович Н. П. Миклашевич Е. Ю.",
                    "Frame": "",
                    "Classroom": ""
                },
                {
                    "Time": "14:15",
                    "Matter": "(Лаб.) Информатика, 1/2 группы ",
                    "Teacher": "доц. Евтухова Т. Е.",
                    "Frame": "20",
                    "Classroom": "301"
                },
                {
                    "Time": "14:15",
                    "Matter": "(Лаб.) Информатика, 1/2 группы ",
                    "Teacher": "доц. Евтухова Т. Е.",
                    "Frame": "20",
                    "Classroom": "303"
                },
                {
                    "Time": "16:00",
                    "Matter": "Кураторский час / информационный час",
                    "Teacher": "зам.дек. Суша Ю. И.",
                    "Frame": "20",
                    "Classroom": "406"
                }
            ],
            "Суббота": [
                {
                    "Time": "08:00",
                    "Matter": "ОИЗ Физика",
                    "Teacher": "проф. Князев М. А.",
                    "Frame": "17",
                    "Classroom": "2П"
                },
                {
                    "Time": "09:55",
                    "Matter": "(Лекц.) Химия",
                    "Teacher": "доц. Бурак Г. А.",
                    "Frame": "11",
                    "Classroom": "507"
                },
                {
                    "Time": "11:40",
                    "Matter": "(Лекц.) Инженерная графика",
                    "Teacher": "ст.пр. Хмельницкая Л. В.",
                    "Frame": "11",
                    "Classroom": "507"
                },
                {
                    "Time": "13:55",
                    "Matter": "ОИЗ, Инженерная графика",
                    "Teacher": "ст.пр. Хмельницкая Л. В.",
                    "Frame": "8",
                    "Classroom": "3П"
                }
            ]
        }
    ]
}